fx_pairs/backtest.py
fx_pairs/instruments.py
fx_pairs/prices.py
fx_pairs/prices_etl.py
fx_pairs/strategy.py
fx_pairs/system.py
fx_pairs/tradingo.py
fx_pairs/universe.yml
fx_pairs-0.0.6.dist-info/METADATA
fx_pairs-0.0.6.dist-info/WHEEL
fx_pairs-0.0.6.dist-info/top_level.txt
fx_pairs-0.0.6.dist-info/RECORD
